phren/__init__.py
phren/main.py
renph-1.0.0.dist-info/LICENSE
renph-1.0.0.dist-info/METADATA
renph-1.0.0.dist-info/WHEEL
renph-1.0.0.dist-info/entry_points.txt
renph-1.0.0.dist-info/top_level.txt
renph-1.0.0.dist-info/RECORD
